<?xml version="1.0" encoding="UTF-8"?>
<!DOCTYPE struts-config PUBLIC "-//Apache Software Foundation//DTD Struts Configuration 1.2//EN" "http://struts.apache.org/dtds/struts-config_1_2.dtd">
<struts-config>
	<global-exceptions />
	<global-forwards />
	<action-mappings>
		<action path="/QueryTable"
			type="com.wireless.Actions.tableSelect.QueryTableAction" scope="request">
		</action>
		<action path="/QueryOrder"
			type="com.wireless.Actions.dishesOrder.QueryOrderAction" scope="request">
		</action>
		<action path="/QueryMenu" type="com.wireless.Actions.dishesOrder.QueryMenuAction"
			scope="request">
		</action>
		<action path="/CancelOrder"
			type="com.wireless.Actions.tableSelect.CancelOrderAction" scope="request">
		</action>
		<action path="/InsertOrder"
			type="com.wireless.Actions.dishesOrder.InsertOrderAction" scope="request">
		</action>
		<action path="/PrintOrder" type="com.wireless.Actions.payment.PrintOrderAction"
			scope="request">
		</action>
		<action path="/PayOrder" type="com.wireless.Actions.payment.PayOrderAction"
			scope="request">
		</action>
		<action path="/QueryMember" type="com.wireless.Actions.payment.QueryMemberAction"
			scope="request">
		</action>
		<action path="/QueryStaff" type="com.wireless.Actions.login.QueryStaffAction"
			scope="request">
		</action>
		<action path="/QueryMerger"
			type="com.wireless.Actions.tableSelect.QueryMergerAction" scope="request">
		</action>
		<action path="/TransTable"
			type="com.wireless.Actions.tableSelect.TransTableAction" scope="request">
		</action>
		<action path="/InsertTable"
			type="com.wireless.Actions.dishesOrder.InsertTableAction" scope="request">
		</action>
		<action path="/CancelTable"
			type="com.wireless.Actions.dishesOrder.CancelTableAction" scope="request">
		</action>
		<action path="/VerifyPwd" type="com.wireless.Actions.dishesOrder.VerifyPwdAction"
			scope="request">
		</action>
		<action path="/QueryRestaurant" type="com.wireless.Actions.login.QueryRestaurantAction"
			scope="request">
		</action>
		<action path="/QueryToday" type="com.wireless.Actions.orderMgr.QueryTodayAction"
			scope="request">
		</action>
		<action path="/QueryTodayAdv"
			type="com.wireless.Actions.orderMgr.QueryTodayAdvAction" scope="request">
		</action>
		<action path="/UpdateOrder2" type="com.wireless.Actions.orderMgr.UpdateOrderAction2"
			scope="request">
		</action>
		<action path="/QueryDetail" type="com.wireless.Actions.orderMgr.QueryDetailAction"
			scope="request">
		</action>
		<action path="/QueryShift" type="com.wireless.Actions.shift.QueryShiftAction"
			scope="request">
		</action>
		<action path="/DoShift" type="com.wireless.Actions.shift.DoShiftAction"
			scope="request">
		</action>
		<action path="/QueryMenuMgr" type="com.wireless.Actions.menuMgr.QueryMenuMgrAction"
			scope="request">
		</action>
		<action path="/UpdateMenu" type="com.wireless.Actions.menuMgr.UpdateMenuAction"
			scope="request">
		</action>
		<action path="/DeleteMenu" type="com.wireless.Actions.menuMgr.DeleteMenuAction"
			scope="request">
		</action>
		<action path="/InsertMenu" type="com.wireless.Actions.menuMgr.InsertMenuAction"
			scope="request">
		</action>
		<action path="/MenuStatistics"
			type="com.wireless.Actions.billStatistics.MenuStatisticsAction" scope="request">
		</action>
		<action path="/QuerySupplierMgr"
			type="com.wireless.Actions.supplierMgr.QuerySupplierMgrAction" scope="request">
		</action>
		<action path="/DeleteSupplier"
			type="com.wireless.Actions.supplierMgr.DeleteSupplierAction" scope="request">
		</action>
		<action path="/InsertSupplier"
			type="com.wireless.Actions.supplierMgr.InsertSupplierAction" scope="request">
		</action>
		<action path="/UpdateSupplier"
			type="com.wireless.Actions.supplierMgr.UpdateSupplierAction" scope="request">
		</action>
		<action path="/QueryKitchenMgr"
			type="com.wireless.Actions.kitchenMgr.QueryKitchenMgrAction" scope="request">
		</action>
		<action path="/QueryDepartment"
			type="com.wireless.Actions.deptMgr.QueryDepartmentMgrAction" scope="request">
		</action>
		<action path="/UpdateKitchen"
			type="com.wireless.Actions.kitchenMgr.UpdateKitchenAction" scope="request">
		</action>
		<action path="/kitchenStatistics"
			type="com.wireless.Actions.billStatistics.KitchenStatisticsAction" scope="request">
		</action>
		<action path="/UpdateDepartment"
			type="com.wireless.Actions.deptMgr.UpdateDepartmentAction" scope="request">
		</action>
		<action path="/QueryMaterialMgr"
			type="com.wireless.Actions.inventoryMgr.materialManagement.QueryMaterialMgrAction"
			scope="request">
		</action>
		<action path="/UpdateMaterial"
			type="com.wireless.Actions.inventoryMgr.materialManagement.UpdateMaterialAction" scope="request">
		</action>
		<action path="/DeleteMaterial"
			type="com.wireless.Actions.inventoryMgr.materialManagement.DeleteMaterialAciton" scope="request">
		</action>
		<action path="/InsertMaterial"
			type="com.wireless.Actions.inventoryMgr.materialManagement.InsertMaterialAction" scope="request">
		</action>
		<action path="/InventoryIn"
			type="com.wireless.Actions.inventoryMgr.inventoryOperation.InventoryInAction" scope="request">
		</action>
		<action path="/InventoryOut"
			type="com.wireless.Actions.inventoryMgr.inventoryOperation.InventoryOutAction" scope="request">
		</action>
		<action path="/InventoryChange"
			type="com.wireless.Actions.inventoryMgr.inventoryOperation.InventoryChangeAction" scope="request">
		</action>
		<action path="/InventoryInStatDetail"
			type="com.wireless.Actions.inventoryMgr.statistics.StatInventoryInDetail" scope="request">
		</action>
		<action path="/QueryCurrStock" type="com.wireless.Actions.inventoryMgr.QueryCurrStock"
			scope="request">
		</action>
		<action path="/InventoryCheck"
			type="com.wireless.Actions.inventoryMgr.inventoryOperation.InventoryCheckAction" scope="request">
		</action>
		<action path="/QueryFoodMaterial" type="com.wireless.Actions.menuMgr.QueryFoodMaterial"
			scope="request">
		</action>
		<action path="/InsertFoodMaterial"
			type="com.wireless.Actions.menuMgr.InsertFoodMaterialAction" scope="request">
		</action>
		<action path="/DeleteFoodMaterial"
			type="com.wireless.Actions.menuMgr.DeleteFoodMaterialAction" scope="request">
		</action>
		<action path="/InventoryInStatByMaterial"
			type="com.wireless.Actions.inventoryMgr.statistics.StatInventoryInByMaterial"
			scope="request">
		</action>
		<action path="/InventoryInStatByDept"
			type="com.wireless.Actions.inventoryMgr.statistics.StatInventoryInByDept" scope="request">
		</action>
		<action path="/InventoryInStatBySupplier"
			type="com.wireless.Actions.inventoryMgr.statistics.StatInventoryInBySupplier"
			scope="request">
		</action>
		<action path="/InventoryOutStatDetail"
			type="com.wireless.Actions.inventoryMgr.statistics.StatInventoryOutDetail"
			scope="request">
		</action>
		<action path="/InventoryOutStatByMaterial"
			type="com.wireless.Actions.inventoryMgr.statistics.StatInventoryOutByMaterial"
			scope="request">
		</action>
		<action path="/InventoryOutStatByDept"
			type="com.wireless.Actions.inventoryMgr.statistics.StatInventoryOutByDept"
			scope="request">
		</action>
		<action path="/InventoryOutStatByReason"
			type="com.wireless.Actions.inventoryMgr.statistics.StatInventoryOutByReason"
			scope="request">
		</action>
		<action path="/InventoryChangeStatDetail"
			type="com.wireless.Actions.inventoryMgr.statistics.StatInventoryChangeDetail"
			scope="request">
		</action>
		<action path="/InventoryChangeStatByMaterial"
			type="com.wireless.Actions.inventoryMgr.statistics.StatInventoryChangeByMaterial"
			scope="request">
		</action>
		<action path="/InventoryChangeStatByOutDept"
			type="com.wireless.Actions.inventoryMgr.statistics.StatInventoryChangeByOutDept"
			scope="request">
		</action>
		<action path="/InventoryChangeStatByInDept"
			type="com.wireless.Actions.inventoryMgr.statistics.StatInventoryChangeByInDept"
			scope="request">
		</action>
		<action path="/InventoryCostStatDetail"
			type="com.wireless.Actions.inventoryMgr.statistics.StatInventoryCostDetail"
			scope="request">
		</action>
		<action path="/InventoryCostStatByMaterial"
			type="com.wireless.Actions.inventoryMgr.statistics.StatInventoryCostByMaterial"
			scope="request">
		</action>
		<action path="/InventoryCostStatByDept"
			type="com.wireless.Actions.inventoryMgr.statistics.StatInventoryCostByDept"
			scope="request">
		</action>
		<action path="/InventoryAllStatDetail"
			type="com.wireless.Actions.inventoryMgr.statistics.StatInventoryAllDetail"
			scope="request">
		</action>
		<action path="/InventoryAllStatByMaterial"
			type="com.wireless.Actions.inventoryMgr.statistics.StatInventoryAllByMaterial"
			scope="request">
		</action>
		<action path="/InventoryAllStatByDept"
			type="com.wireless.Actions.inventoryMgr.statistics.StatInventoryAllByDept"
			scope="request">
		</action>
		<action path="/InventoryCheckStatDetail"
			type="com.wireless.Actions.inventoryMgr.statistics.StatInventoryCheckDetail"
			scope="request">
		</action>
		<action path="/InventoryCheckStatSum"
			type="com.wireless.Actions.inventoryMgr.statistics.StatInventoryCheckSum" scope="request">
		</action>
		<action path="/InventoryReturn"
			type="com.wireless.Actions.inventoryMgr.inventoryOperation.InventoryReturnAction" scope="request">
		</action>
		<action path="/InventoryReturnStatDetail"
			type="com.wireless.Actions.inventoryMgr.statistics.StatInventoryReturnDetail"
			scope="request">
		</action>
		<action path="/InventoryReturnStatByMaterial"
			type="com.wireless.Actions.inventoryMgr.statistics.StatInventoryReturnByMaterial"
			scope="request">
		</action>
		<action path="/InventoryReturnStatByDept"
			type="com.wireless.Actions.inventoryMgr.statistics.StatInventoryReturnByDept"
			scope="request">
		</action>
		<action path="/InventoryReturnStatBySupplier"
			type="com.wireless.Actions.inventoryMgr.statistics.StatInventoryReturnBySupplier"
			scope="request">
		</action>
		<action path="/QueryMaterialCate"
			type="com.wireless.Actions.materialCateMgr.QueryMaterialCateMgrAction"
			scope="request">
		</action>
		<action path="/UpdateMaterialCate"
			type="com.wireless.Actions.materialCateMgr.UpdateMaterialCateAction"
			scope="request">
		</action>
		<action path="/QueryRegion"
			type="com.wireless.Actions.regionMgr.QueryRegionMgrAction" scope="request">
		</action>
		<action path="/UpdateRegion"
			type="com.wireless.Actions.regionMgr.UpdateRegionAction" scope="request">
		</action>
		<action path="/DeleteTable" type="com.wireless.Actions.tableMgr.DeleteTableAction"
			scope="request">
		</action>
		<action path="/UpdateTable" type="com.wireless.Actions.tableMgr.UpdateTableAction"
			scope="request">
		</action>
		<action path="/InsertTable" type="com.wireless.Actions.tableMgr.InsertTableAction"
			scope="request">
		</action>
		<action path="/QueryTaste" type="com.wireless.Actions.tasteMgr.QueryTasteAction"
			scope="request">
		</action>
		<action path="/InsertTaste" type="com.wireless.Actions.tasteMgr.InsertTasteAction"
			scope="request">
		</action>
		<action path="/UpdateTaste" type="com.wireless.Actions.tasteMgr.UpdateTasteAction"
			scope="request">
		</action>
		<action path="/DeleteTaste" type="com.wireless.Actions.tasteMgr.DeleteTasteAction"
			scope="request">
		</action>
		<action path="/QueryTerminal"
			type="com.wireless.Actions.terminalMgr.QueryTerminalAction" scope="request">
		</action>
		<action path="/SetTerminal"
			type="com.wireless.Actions.terminalMgr.SetTerminalAction" scope="request">
		</action>
		<action path="/InsertStaff" type="com.wireless.Actions.staffMgr.InsertStaffAction"
			scope="request">
		</action>
		<action path="/DeleteStaff" type="com.wireless.Actions.staffMgr.DeleteStaffAction"
			scope="request">
		</action>
		<action path="/UpdateStaff" type="com.wireless.Actions.staffMgr.UpdateStaffAction"
			scope="request">
		</action>
		<action path="/ResetStaffPassword"
			type="com.wireless.Actions.staffMgr.ResetPwdStaffAction" scope="request">
		</action>
		<action path="/deptStatistics"
			type="com.wireless.Actions.billStatistics.DeptStatisticsAction" scope="request">
		</action>
		<action path="/regionStatistics"
			type="com.wireless.Actions.billStatistics.RegionStatisticsAction" scope="request">
		</action>
		<action path="/DiscountStatDetail"
			type="com.wireless.Actions.billStatistics.DiscountStatisticsDetailAction" scope="request">
		</action>
		<action path="/shiftStat"
			type="com.wireless.Actions.billStatistics.ShiftStatisticsAction" scope="request">
		</action>
		<action path="/shiftStatDetail"
			type="com.wireless.Actions.billStatistics.ShiftStatDetailAction" scope="request">
		</action>
		<action path="/DailySettleCheck"
			type="com.wireless.Actions.dailySettle.DailySettleCheckAction" scope="request">
		</action>
		<action path="/DailySettleExec"
			type="com.wireless.Actions.dailySettle.DailySettleExecAction" scope="request">
		</action>
		<action path="/QueryHistory" type="com.wireless.Actions.billHistory.QueryHistoryAction"
			scope="request">
		</action>
		<action path="/QueryHistoryAdv" type="com.wireless.Actions.billHistory.QueryHistoryAdvAction"
			scope="request">
		</action>
		<action path="/dailySettleStat"
			type="com.wireless.Actions.billHistory.DailySettleStatisticsAction" scope="request">
		</action>
		<action path="/dailySettleStatDetail"
			type="com.wireless.Actions.billHistory.DailySettleStatDetailAction" scope="request">
		</action>
		<action path="/SetPassword"
			type="com.wireless.Actions.passwordConfig.SetPasswordAction" scope="request">
		</action>
		<action path="/businessStatistics"
			type="com.wireless.Actions.billStatistics.BusinessStatisticsAction" scope="request">
		</action>
		<action path="/supplierStatistics"
			type="com.wireless.Actions.inventoryMgr.statistics.supplierStatisticsAction" scope="request">
		</action>
		<action path="/InventoryAnalysisCurrent"
			type="com.wireless.Actions.inventoryMgr.statistics.InventoryAnalysisCurrent" scope="request">
		</action>
		<action path="/InventoryAnalysisInOutSum"
			type="com.wireless.Actions.inventoryMgr.statistics.InventoryAnalysisInOutSum" scope="request">
		</action>
		<action path="/InventoryAnalysis"
			type="com.wireless.Actions.inventoryMgr.statistics.InventoryAnalysis" scope="request">
		</action>
		<action path="/SalesSubStatistics" type="com.wireless.Actions.billHistory.SalesSubStatisticsAction" scope="request"></action>
		<action path="/QueryDeptTree" type="com.wireless.Actions.deptMgr.QueryDeptTreeAction" scope="request"></action>
		<action path="/QueryBackFood" type="com.wireless.Actions.billHistory.QueryBackFoodAction" scope="request"></action>
		<action path="/UpdateFoodMaterial" type="com.wireless.Actions.menuMgr.UpdateFoodMaterialAction" scope="request"></action>
	</action-mappings>
	<message-resources parameter="com.yourcompany.struts.ApplicationResources" />
</struts-config>